[
  {
    "model_name": "yolov5n",
    "model_path": "yolov5nu.pt",
    "trained_model_path": "yolo_litter_detection_part1/yolov5n/weights/best.pt",
    "size_mb": 5.305060386657715,
    "parameters": 2654816,
    "training_time_hours": 0.026387308107482063,
    "default_map50": 0.19141677764002488,
    "default_map50_95": 0.07792918649197528,
    "best_confidence": 0.001,
    "optimized_map50": 0.19141677764002488,
    "optimized_map50_95": 0.07792918649197528,
    "map50_improvement": 0.0,
    "map50_95_improvement": 0.0,
    "avg_inference_time": 0.07561044216156006,
    "fps": 13.22568644504495,
    "avg_inference_time_yolo": 0.0028686442052970273,
    "fps_yolo": 348.5967336602684,
    "confidence_results": [
      {
        "confidence": 0.001,
        "mAP50": 0.21668470233116616,
        "mAP50_95": 0.09199000777763464
      },
      {
        "confidence": 0.1,
        "mAP50": 0.0,
        "mAP50_95": 0.0
      },
      {
        "confidence": 0.2,
        "mAP50": 0.0,
        "mAP50_95": 0.0
      },
      {
        "confidence": 0.3,
        "mAP50": 0.0,
        "mAP50_95": 0.0
      },
      {
        "confidence": 0.4,
        "mAP50": 0.0,
        "mAP50_95": 0.0
      },
      {
        "confidence": 0.5,
        "mAP50": 0.0,
        "mAP50_95": 0.0
      },
      {
        "confidence": 0.6,
        "mAP50": 0.0,
        "mAP50_95": 0.0
      },
      {
        "confidence": 0.7,
        "mAP50": 0.0,
        "mAP50_95": 0.0
      },
      {
        "confidence": 0.8,
        "mAP50": 0.0,
        "mAP50_95": 0.0
      },
      {
        "confidence": 0.9,
        "mAP50": 0.0,
        "mAP50_95": 0.0
      },
      {
        "confidence": 0.95,
        "mAP50": 0.0,
        "mAP50_95": 0.0
      }
    ],
    "completed_at": "2025-07-04T03:18:39.139542",
    "part": 1
  }
]